stagemodel/__init__.py
stagemodel/composite_model.py
stagemodel/node_model.py
stagemodel/utils.py
stagemodel-0.0.6.dist-info/LICENSE
stagemodel-0.0.6.dist-info/METADATA
stagemodel-0.0.6.dist-info/WHEEL
stagemodel-0.0.6.dist-info/top_level.txt
stagemodel-0.0.6.dist-info/RECORD
