Metadata-Version: 2.1
Name: stagemodel
Version: 0.0.6
Summary: Stagewise models
Author-email: IHME Math Sciences <ihme.math.sciences@gmail.com>
License: BSD 2-Clause License
Project-URL: github, https://github.com/ihmeuw-msca/stagemodel
Requires-Python: >=3.10
License-File: LICENSE
Requires-Dist: numpy
Requires-Dist: scipy
Requires-Dist: pandas
Requires-Dist: xarray
Requires-Dist: mrtool >=0.1.4
Provides-Extra: test
Requires-Dist: pytest ; extra == 'test'
